drf_json_patch-0.1.0.dist-info/WHEEL
drf_json_patch-0.1.0.dist-info/metadata.json
drf_json_patch-0.1.0.dist-info/RECORD
drf_json_patch-0.1.0.dist-info/DESCRIPTION.rst
drf_json_patch-0.1.0.dist-info/METADATA
drf_json_patch-0.1.0.dist-info/top_level.txt
rest_framework_json_patch/mixins.py
rest_framework_json_patch/__init__.py
