Metadata-Version: 2.0
Name: drf-json-patch
Version: 0.1.0
Summary: JSON Patch support for Django REST Framework.
Home-page: https://github.com/kevin-brown/rest_framework_json_patch
Author: Kevin Brown
Author-email: kevin@kevinbrown.in
License: MIT
Keywords: rest_framework_json_patch
Platform: UNKNOWN
Classifier: Development Status :: 2 - Pre-Alpha
Classifier: Intended Audience :: Developers
Classifier: License :: OSI Approved :: MIT License
Classifier: Natural Language :: English
Classifier: Programming Language :: Python :: 2
Classifier: Programming Language :: Python :: 2.7
Classifier: Programming Language :: Python :: 3
Classifier: Programming Language :: Python :: 3.2
Classifier: Programming Language :: Python :: 3.3
Classifier: Programming Language :: Python :: 3.4
Requires-Dist: jsonpatch
